odoo/addons/base_external_dbsource_mssql/README.rst
odoo/addons/base_external_dbsource_mssql/__init__.py
odoo/addons/base_external_dbsource_mssql/__manifest__.py
odoo/addons/base_external_dbsource_mssql/demo/base_external_dbsource.xml
odoo/addons/base_external_dbsource_mssql/i18n/base_external_dbsource_mssql.pot
odoo/addons/base_external_dbsource_mssql/i18n/de.po
odoo/addons/base_external_dbsource_mssql/i18n/es.po
odoo/addons/base_external_dbsource_mssql/i18n/hr.po
odoo/addons/base_external_dbsource_mssql/i18n/nl_NL.po
odoo/addons/base_external_dbsource_mssql/i18n/pt_BR.po
odoo/addons/base_external_dbsource_mssql/i18n/sl.po
odoo/addons/base_external_dbsource_mssql/i18n/tr.po
odoo/addons/base_external_dbsource_mssql/models/__init__.py
odoo/addons/base_external_dbsource_mssql/models/base_external_dbsource.py
odoo/addons/base_external_dbsource_mssql/readme/CONFIGURE.rst
odoo/addons/base_external_dbsource_mssql/readme/CONTRIBUTORS.rst
odoo/addons/base_external_dbsource_mssql/readme/DESCRIPTION.rst
odoo/addons/base_external_dbsource_mssql/readme/INSTALL.rst
odoo/addons/base_external_dbsource_mssql/readme/ROADMAP.rst
odoo/addons/base_external_dbsource_mssql/readme/USAGE.rst
odoo/addons/base_external_dbsource_mssql/static/description/icon.png
odoo/addons/base_external_dbsource_mssql/static/description/index.html
odoo/addons/base_external_dbsource_mssql/tests/__init__.py
odoo/addons/base_external_dbsource_mssql/tests/test_base_external_dbsource.py
odoo13_addon_base_external_dbsource_mssql-13.0.1.0.1.dist-info/METADATA
odoo13_addon_base_external_dbsource_mssql-13.0.1.0.1.dist-info/WHEEL
odoo13_addon_base_external_dbsource_mssql-13.0.1.0.1.dist-info/top_level.txt
odoo13_addon_base_external_dbsource_mssql-13.0.1.0.1.dist-info/RECORD
